<?xml version="1.0" encoding="UTF-8" standalone="yes"?>
<plugins>
    <pluginInfo plugin-name="Kony Studio" plugin-id="com.pat.tool.keditor.KEditorPlugin" version-no="5.5.37.QA_v201311181450"/>
    <pluginInfo plugin-name="Third Party Jars Plug-in" version-no="5.5.9.QA_v201310211248"/>
    <pluginInfo plugin-name="Soap UI Plugin" plugin-id="com.pat.soapui.SoapUIPlugin" version-no="5.5.5.QA_v201310211059"/>
    <pluginInfo plugin-name="Kony Codegenerator" version-no="5.5.27.QA_v201311152222"/>
    <pluginInfo plugin-name="KonyHelp Plug-in" plugin-id="com.kony.help.Activator" version-no="5.5.9.QA_v201311181805"/>
    <pluginInfo plugin-name="Nativecodegen" plugin-id="com.kony.nativecodegen.NativeCodeGenPlugin" version-no="5.5.2.QA_v201310211425"/>
    <pluginInfo plugin-name="Kony Studio Licensing" version-no="5.5.0.beta2_v201309291420"/>
    <pluginInfo plugin-name="CloudMiddlewarePlugin" plugin-id="com.kony.cloudmiddleware.Activator" version-no="5.5.13.QA_v201310281034"/>
    <pluginInfo plugin-name="CloudThirdPartyPlugin" plugin-id="com.kony.cloudthirdparty.Activator" version-no="5.5.13.QA_v201310281034"/>
    <pluginInfo plugin-name="Tablet Android" plugin-id="com.pat.android.Activator" version-no="5.5.26.QA_v201311181123"/>
    <pluginInfo plugin-name="Blackberry &amp; J2ME" plugin-id="com.pat.j2me.J2MEPlugin" version-no="5.5.13.QA_v201311042222"/>
    <pluginInfo plugin-name="Winmobile Plug-in" plugin-id="com.pat.winmobile.WinMobilePlugin" version-no="5.5.8.QA_v201311181551"/>
    <pluginInfo plugin-name="Windows Phone 8 Plug-in" plugin-id="com.kony.windows.WindowsPhone8Plugin" version-no="5.5.9.QA_v201311181152"/>
    <pluginInfo plugin-name="Windows 8 Plug-in" plugin-id="com.kony.windows.Windows8Plugin" version-no="5.5.9.QA_v201311181242"/>
    <pluginInfo plugin-name="Android" plugin-id="com.pat.android.Activator" version-no="5.5.26.QA_v201311152220"/>
    <pluginInfo plugin-name="ThinClient" plugin-id="thinclientplugin.Activator" version-no="5.5.13.QA_v201311181520"/>
    <pluginInfo plugin-name="Windows Desktop Plug-in" plugin-id="com.kony.windows.WinDesktopPlugin" version-no="5.5.8.QA_v201311181206"/>
    <pluginInfo plugin-name="SPA" version-no="5.5.15.QA_v201311152117"/>
    <pluginInfo plugin-name="Desktop Web" version-no="5.5.15.QA_v201311181418"/>
    <pluginInfo plugin-name="Kony Sync" plugin-id="com.kony.sync.ide.SyncPlugin" version-no="5.5.7.GA_v201310241728"/>
    <pluginInfo plugin-name="Kony Web Commons" plugin-id="com.kony.web.Activator" version-no="5.5.5.QA_v201310291642"/>
    <pluginInfo plugin-name="iOS Plugin" plugin-id="iosplugin.Activator" version-no="5.5.17.QA_v201311182138"/>
</plugins>
